povplot.py
povplot-1.0b0.dist-info/DESCRIPTION.rst
povplot-1.0b0.dist-info/METADATA
povplot-1.0b0.dist-info/RECORD
povplot-1.0b0.dist-info/WHEEL
povplot-1.0b0.dist-info/metadata.json
povplot-1.0b0.dist-info/top_level.txt
