Metadata-Version: 2.0
Name: povplot
Version: 1.0b0
Summary: A library for rendering triangular grids with Povray
Home-page: https://github.com/evalf/povplot
Author: Evalf
Author-email: info@evalf.com
License: MIT
Download-URL: https://github.com/evalf/povplot/releases
Platform: UNKNOWN
Requires-Python: >=3.5
Provides-Extra: docs
Requires-Dist: jinja2
Requires-Dist: matplotlib
Requires-Dist: numpy
Provides-Extra: docs
Requires-Dist: Sphinx; extra == 'docs'
